classWeightLearn/__init__.py
classWeightLearn/main.py
classWeightLearn-1.0.0.dist-info/METADATA
classWeightLearn-1.0.0.dist-info/WHEEL
classWeightLearn-1.0.0.dist-info/top_level.txt
classWeightLearn-1.0.0.dist-info/RECORD
