Metadata-Version: 2.1
Name: classWeightLearn
Version: 1.0.0
Summary: Optuna Class Weight Cost-Sensitive Learning
Home-page: 
Author: Mahayasa Adiputra
Author-email: mahayasa.a@kkumail.com
Requires-Dist: scikit-learn (==1.6.1)
Requires-Dist: sdv (==1.18.0)
Requires-Dist: pandas (==2.0.3)
Requires-Dist: optuna (==4.2.0)
